README.md
setup.py
domophoenix/__init__.py
domophoenix/base_plotter.py
domophoenix/domophoenix.py
domophoenix.egg-info/PKG-INFO
domophoenix.egg-info/SOURCES.txt
domophoenix.egg-info/dependency_links.txt
domophoenix.egg-info/top_level.txt