Metadata-Version: 2.1
Name: domophoenix
Version: 1.0.0
Summary: Create beautiful Domo Phoenix charts with Python in Jupyter
Home-page: https://www.domo.com
Author: John Woodruff
Author-email: johnwoodruff91@gmail.com
License: SEE LICENSE
Platform: UNKNOWN
